selectpy/Select.py
selectpy/__init__.py
selectpy-0.0.4.dist-info/LICENSE
selectpy-0.0.4.dist-info/METADATA
selectpy-0.0.4.dist-info/WHEEL
selectpy-0.0.4.dist-info/top_level.txt
selectpy-0.0.4.dist-info/RECORD
