Metadata-Version: 2.1
Name: selectpy
Version: 0.0.4
Summary: A fully customizable selection menu for python
Author: Soham P
Author-email: <sohxmp1204@gmail.com>
Keywords: python,select,select menu,terminal menu,python menu,python select menu
License-File: LICENSE
Requires-Dist: rich
Requires-Dist: python-yakh
